CHANGES.txt
MANIFEST.in
README.txt
setup.py
src/sa_mysql_dt/__init__.py
src/sa_mysql_dt/field.py
src/sa_mysql_dt/tests.py
src/sa_mysql_dt.egg-info/PKG-INFO
src/sa_mysql_dt.egg-info/SOURCES.txt
src/sa_mysql_dt.egg-info/dependency_links.txt
src/sa_mysql_dt.egg-info/not-zip-safe
src/sa_mysql_dt.egg-info/requires.txt
src/sa_mysql_dt.egg-info/top_level.txt