Metadata-Version: 1.0
Name: sa-mysql-dt
Version: 0.1.2
Summary: Alternative implementation of DateTime column for MySQL.
Home-page: UNKNOWN
Author: Martijn Faassen
Author-email: faassen@startifact.com
License: UNKNOWN
Keywords: sqlalchemy MySQL
Platform: UNKNOWN
